corncob/__init__.py
corncob/command_line.py
corncob/corncob.py
corncob-0.0.1.dist-info/LICENSE
corncob-0.0.1.dist-info/METADATA
corncob-0.0.1.dist-info/WHEEL
corncob-0.0.1.dist-info/entry_points.txt
corncob-0.0.1.dist-info/top_level.txt
corncob-0.0.1.dist-info/RECORD
