Metadata-Version: 2.1
Name: corncob
Version: 0.0.1
Summary: beta-binomial based testing of count data
Home-page: https://github.com/jgolob/corncob
Author: Jonathan Golob
Author-email: j-dev@golob.org
License: UNKNOWN
Platform: UNKNOWN
Classifier: Programming Language :: Python :: 3
Classifier: License :: OSI Approved :: MIT License
Classifier: Operating System :: OS Independent
Requires-Python: >=3.6
Requires-Dist: pandas
Requires-Dist: scipy
Requires-Dist: numpy
Requires-Dist: statsmodels
